ticktick/__init__.py
ticktick/objectid.py
ticktick/ticktick.py
ticktick-0.1.4.dist-info/LICENSE
ticktick-0.1.4.dist-info/METADATA
ticktick-0.1.4.dist-info/WHEEL
ticktick-0.1.4.dist-info/top_level.txt
ticktick-0.1.4.dist-info/RECORD
