Metadata-Version: 2.1
Name: ticktick
Version: 0.1.4
Summary: Python API for TickTick
Home-page: https://github.com/gasslion/ticktick-python
Author: Leo Zhou
Author-email: glasslion@gmail.com
License: MIT license
Keywords: ticktick
Platform: UNKNOWN
Classifier: Development Status :: 2 - Pre-Alpha
Classifier: Intended Audience :: Developers
Classifier: License :: OSI Approved :: MIT License
Classifier: Natural Language :: English
Classifier: Programming Language :: Python :: 2
Classifier: Programming Language :: Python :: 2.7
Classifier: Programming Language :: Python :: 3
Classifier: Programming Language :: Python :: 3.4
Classifier: Programming Language :: Python :: 3.5
Classifier: Programming Language :: Python :: 3.6
Classifier: Programming Language :: Python :: 3.7
Requires-Dist: requests
Requires-Dist: addict
Requires-Dist: arrow
Requires-Dist: six
Requires-Dist: bson
